bog_builder/__init__.py
bog_builder/analyzer.py
bog_builder/builder.py
bog_builder/generate_llm_docs.py
bog_builder/models.py
pybog-0.1.6.dist-info/licenses/LICENSE
pybog-0.1.6.dist-info/METADATA
pybog-0.1.6.dist-info/WHEEL
pybog-0.1.6.dist-info/top_level.txt
pybog-0.1.6.dist-info/RECORD
