Metadata-Version: 2.4
Name: pybog
Version: 0.1.6
Summary: A Python toolkit for programmatically generating Tridium Niagara .bog files for HVAC controls.
Author-email: Ben Bartling <ben.bartling@gmail.com>
License: MIT
Project-URL: Homepage, https://github.com/bbartling/pybog
Project-URL: Repository, https://github.com/bbartling/pybog
Project-URL: YouTube Channel, https://www.youtube.com/@TalkShopWithBen
Classifier: Development Status :: 4 - Beta
Classifier: Programming Language :: Python :: 3
Classifier: License :: OSI Approved :: MIT License
Classifier: Operating System :: OS Independent
Classifier: Intended Audience :: Developers
Classifier: Intended Audience :: End Users/Desktop
Classifier: Topic :: Scientific/Engineering
Classifier: Topic :: Software Development :: Build Tools
Classifier: Topic :: System :: Hardware :: Universal Serial Bus (USB)
Requires-Python: >=3.8
License-File: LICENSE
Requires-Dist: pydantic
Provides-Extra: dev
Requires-Dist: pytest; extra == "dev"
Requires-Dist: black; extra == "dev"
Requires-Dist: matplotlib; extra == "dev"
Requires-Dist: pydantic; extra == "dev"
Dynamic: license-file
